Workbook

Sheet RAW_INPUT
A1: RAW TRADE SIGNALS IMPORT
A2: Stock | B2: Entry Date | C2: Entry Price | D2: Exit Date | E2: Close Price | F2: Provided Return %
A3: Gujarat Alkalies & C.. | B3: 2013-03-28 | C3: 215 | D3: 2013-06-28 | E3: 178.05 | F3: -17.19
A4: Rain Industries Ltd. | B4: 2013-03-28 | C4: 47.5 | D4: 2013-06-28 | E4: 40 | F4: -15.79
A5: CIE Automotive India.. | B5: 2013-06-28 | C5: 59.45 | D5: 2013-09-30 | E5: 66.8 | F5: 12.36
A6: Suven Life Sciences .. | B6: 2013-09-30 | C6: 42.95 | D6: 2013-12-31 | E6: 72.35 | F6: 68.45
A7: Alembic Ltd. | B7: 2013-09-30 | C7: 13.45 | D7: 2013-12-31 | E7: 14.95 | F7: 11.15
A8: Nucleus Software Exp.. | B8: 2013-09-30 | C8: 95.05 | D8: 2014-03-31 | E8: 217.9 | F8: 129.25
A9: Himatsingka Seide Ltd. | B9: 2013-12-31 | C9: 54.65 | D9: 2014-03-31 | E9: 57.4 | F9: 5.03
A10: Vinati Organics Ltd. | B10: 2013-12-31 | C10: 95.35 | D10: 2014-03-31 | E10: 140.52 | F10: 47.37
A11: Ashiana Housing Ltd. | B11: 2013-12-31 | C11: 70 | D11: 2014-03-31 | E11: 88.8 | F11: 26.86
A12: FIEM Industries Ltd. | B12: 2013-12-31 | C12: 172.15 | D12: 2014-03-31 | E12: 206.25 | F12: 19.81
A13: Hindustan Composites.. | B13: 2013-12-31 | C13: 133.33 | D13: 2014-03-31 | E13: 136.67 | F13: 2.51
A14: Igarashi Motors Indi.. | B14: 2013-12-31 | C14: 74.75 | D14: 2014-03-31 | E14: 152.17 | F14: 103.57
... A791: Prudent Corporate Ad.. | B791: 2024-07-31 | C791: 2295.45 | D791: 2024-07-31 | E791: 2295.45 | F791: 0

Sheet TRADE_CALCULATION
A1: INDEPENDENT TRADE-BY-TRADE AUDIT & FORMULA CALCULATIONS
A2: Trade ID | B2: Stock | C2: Entry Date | D2: Exit Date | E2: Duration | F2: Entry Price | G2: Exit Price | H2: Quantity | I2: Allocated Capital | J2: Calculated P&L | K2: Calculated Return % | L2: Provided Return % | M2: Return Difference % | N2: Winning Trade | O2: Losing Trade | P2: Cumulative P&L | Q2: Cumulative Return % | R2: Equity | S2: Running Peak | T2: Drawdown | U2: Drawdown % | V2: Downside Return Sq
A3: =TEXT(1, """T""0000") | B3: =RAW_INPUT!A3 | C3: =RAW_INPUT!B3 | D3: =RAW_INPUT!D3 | E3: =D3-C3 | F3: =RAW_INPUT!C3 | G3: =RAW_INPUT!E3 | H3: =I3/F3 | I3: =METRICS!$C$14 * 0.02 | J3: =(G3-F3)*H3 | K3: =(G3-F3)/F3*100 | L3: =RAW_INPUT!F3 | M3: =K3-L3 | N3: =IF(J3>0, 1, 0) | O3: =IF(J3<0, 1, 0) | P3: =SUM($J$3:J3) | Q3: =P3/METRICS!$C$14*100 | R3: =METRICS!$C$14+P3 | S3: =MAX($R$3:R3) | T3: =R3-S3 | U3: =(R3-S3)/S3*100 | V3: =IF(K3<0, (K3/100)^2, 0)
A4: =TEXT(2, """T""0000") | B4: =RAW_INPUT!A4 | C4: =RAW_INPUT!B4 | D4: =RAW_INPUT!D4 | E4: =D4-C4 | F4: =RAW_INPUT!C4 | G4: =RAW_INPUT!E4 | H4: =I4/F4 | I4: =METRICS!$C$14 * 0.02 | J4: =(G4-F4)*H4 | K4: =(G4-F4)/F4*100 | L4: =RAW_INPUT!F4 | M4: =K4-L4 | N4: =IF(J4>0, 1, 0) | O4: =IF(J4<0, 1, 0) | P4: =SUM($J$3:J4) | Q4: =P4/METRICS!$C$14*100 | R4: =METRICS!$C$14+P4 | S4: =MAX($R$3:R4) | T4: =R4-S4 | U4: =(R4-S4)/S4*100 | V4: =IF(K4<0, (K4/100)^2, 0)
A5: =TEXT(3, """T""0000") | B5: =RAW_INPUT!A5 | C5: =RAW_INPUT!B5 | D5: =RAW_INPUT!D5 | E5: =D5-C5 | F5: =RAW_INPUT!C5 | G5: =RAW_INPUT!E5 | H5: =I5/F5 | I5: =METRICS!$C$14 * 0.02 | J5: =(G5-F5)*H5 | K5: =(G5-F5)/F5*100 | L5: =RAW_INPUT!F5 | M5: =K5-L5 | N5: =IF(J5>0, 1, 0) | O5: =IF(J5<0, 1, 0) | P5: =SUM($J$3:J5) | Q5: =P5/METRICS!$C$14*100 | R5: =METRICS!$C$14+P5 | S5: =MAX($R$3:R5) | T5: =R5-S5 | U5: =(R5-S5)/S5*100 | V5: =IF(K5<0, (K5/100)^2, 0)
A6: =TEXT(4, """T""0000") | B6: =RAW_INPUT!A6 | C6: =RAW_INPUT!B6 | D6: =RAW_INPUT!D6 | E6: =D6-C6 | F6: =RAW_INPUT!C6 | G6: =RAW_INPUT!E6 | H6: =I6/F6 | I6: =METRICS!$C$14 * 0.02 | J6: =(G6-F6)*H6 | K6: =(G6-F6)/F6*100 | L6: =RAW_INPUT!F6 | M6: =K6-L6 | N6: =IF(J6>0, 1, 0) | O6: =IF(J6<0, 1, 0) | P6: =SUM($J$3:J6) | Q6: =P6/METRICS!$C$14*100 | R6: =METRICS!$C$14+P6 | S6: =MAX($R$3:R6) | T6: =R6-S6 | U6: =(R6-S6)/S6*100 | V6: =IF(K6<0, (K6/100)^2, 0)
A7: =TEXT(5, """T""0000") | B7: =RAW_INPUT!A7 | C7: =RAW_INPUT!B7 | D7: =RAW_INPUT!D7 | E7: =D7-C7 | F7: =RAW_INPUT!C7 | G7: =RAW_INPUT!E7 | H7: =I7/F7 | I7: =METRICS!$C$14 * 0.02 | J7: =(G7-F7)*H7 | K7: =(G7-F7)/F7*100 | L7: =RAW_INPUT!F7 | M7: =K7-L7 | N7: =IF(J7>0, 1, 0) | O7: =IF(J7<0, 1, 0) | P7: =SUM($J$3:J7) | Q7: =P7/METRICS!$C$14*100 | R7: =METRICS!$C$14+P7 | S7: =MAX($R$3:R7) | T7: =R7-S7 | U7: =(R7-S7)/S7*100 | V7: =IF(K7<0, (K7/100)^2, 0)
A8: =TEXT(6, """T""0000") | B8: =RAW_INPUT!A8 | C8: =RAW_INPUT!B8 | D8: =RAW_INPUT!D8 | E8: =D8-C8 | F8: =RAW_INPUT!C8 | G8: =RAW_INPUT!E8 | H8: =I8/F8 | I8: =METRICS!$C$14 * 0.02 | J8: =(G8-F8)*H8 | K8: =(G8-F8)/F8*100 | L8: =RAW_INPUT!F8 | M8: =K8-L8 | N8: =IF(J8>0, 1, 0) | O8: =IF(J8<0, 1, 0) | P8: =SUM($J$3:J8) | Q8: =P8/METRICS!$C$14*100 | R8: =METRICS!$C$14+P8 | S8: =MAX($R$3:R8) | T8: =R8-S8 | U8: =(R8-S8)/S8*100 | V8: =IF(K8<0, (K8/100)^2, 0)
A9: =TEXT(7, """T""0000") | B9: =RAW_INPUT!A9 | C9: =RAW_INPUT!B9 | D9: =RAW_INPUT!D9 | E9: =D9-C9 | F9: =RAW_INPUT!C9 | G9: =RAW_INPUT!E9 | H9: =I9/F9 | I9: =METRICS!$C$14 * 0.02 | J9: =(G9-F9)*H9 | K9: =(G9-F9)/F9*100 | L9: =RAW_INPUT!F9 | M9: =K9-L9 | N9: =IF(J9>0, 1, 0) | O9: =IF(J9<0, 1, 0) | P9: =SUM($J$3:J9) | Q9: =P9/METRICS!$C$14*100 | R9: =METRICS!$C$14+P9 | S9: =MAX($R$3:R9) | T9: =R9-S9 | U9: =(R9-S9)/S9*100 | V9: =IF(K9<0, (K9/100)^2, 0)
A10: =TEXT(8, """T""0000") | B10: =RAW_INPUT!A10 | C10: =RAW_INPUT!B10 | D10: =RAW_INPUT!D10 | E10: =D10-C10 | F10: =RAW_INPUT!C10 | G10: =RAW_INPUT!E10 | H10: =I10/F10 | I10: =METRICS!$C$14 * 0.02 | J10: =(G10-F10)*H10 | K10: =(G10-F10)/F10*100 | L10: =RAW_INPUT!F10 | M10: =K10-L10 | N10: =IF(J10>0, 1, 0) | O10: =IF(J10<0, 1, 0) | P10: =SUM($J$3:J10) | Q10: =P10/METRICS!$C$14*100 | R10: =METRICS!$C$14+P10 | S10: =MAX($R$3:R10) | T10: =R10-S10 | U10: =(R10-S10)/S10*100 | V10: =IF(K10<0, (K10/100)^2, 0)
A11: =TEXT(9, """T""0000") | B11: =RAW_INPUT!A11 | C11: =RAW_INPUT!B11 | D11: =RAW_INPUT!D11 | E11: =D11-C11 | F11: =RAW_INPUT!C11 | G11: =RAW_INPUT!E11 | H11: =I11/F11 | I11: =METRICS!$C$14 * 0.02 | J11: =(G11-F11)*H11 | K11: =(G11-F11)/F11*100 | L11: =RAW_INPUT!F11 | M11: =K11-L11 | N11: =IF(J11>0, 1, 0) | O11: =IF(J11<0, 1, 0) | P11: =SUM($J$3:J11) | Q11: =P11/METRICS!$C$14*100 | R11: =METRICS!$C$14+P11 | S11: =MAX($R$3:R11) | T11: =R11-S11 | U11: =(R11-S11)/S11*100 | V11: =IF(K11<0, (K11/100)^2, 0)
A12: =TEXT(10, """T""0000") | B12: =RAW_INPUT!A12 | C12: =RAW_INPUT!B12 | D12: =RAW_INPUT!D12 | E12: =D12-C12 | F12: =RAW_INPUT!C12 | G12: =RAW_INPUT!E12 | H12: =I12/F12 | I12: =METRICS!$C$14 * 0.02 | J12: =(G12-F12)*H12 | K12: =(G12-F12)/F12*100 | L12: =RAW_INPUT!F12 | M12: =K12-L12 | N12: =IF(J12>0, 1, 0) | O12: =IF(J12<0, 1, 0) | P12: =SUM($J$3:J12) | Q12: =P12/METRICS!$C$14*100 | R12: =METRICS!$C$14+P12 | S12: =MAX($R$3:R12) | T12: =R12-S12 | U12: =(R12-S12)/S12*100 | V12: =IF(K12<0, (K12/100)^2, 0)
A13: =TEXT(11, """T""0000") | B13: =RAW_INPUT!A13 | C13: =RAW_INPUT!B13 | D13: =RAW_INPUT!D13 | E13: =D13-C13 | F13: =RAW_INPUT!C13 | G13: =RAW_INPUT!E13 | H13: =I13/F13 | I13: =METRICS!$C$14 * 0.02 | J13: =(G13-F13)*H13 | K13: =(G13-F13)/F13*100 | L13: =RAW_INPUT!F13 | M13: =K13-L13 | N13: =IF(J13>0, 1, 0) | O13: =IF(J13<0, 1, 0) | P13: =SUM($J$3:J13) | Q13: =P13/METRICS!$C$14*100 | R13: =METRICS!$C$14+P13 | S13: =MAX($R$3:R13) | T13: =R13-S13 | U13: =(R13-S13)/S13*100 | V13: =IF(K13<0, (K13/100)^2, 0)
A14: =TEXT(12, """T""0000") | B14: =RAW_INPUT!A14 | C14: =RAW_INPUT!B14 | D14: =RAW_INPUT!D14 | E14: =D14-C14 | F14: =RAW_INPUT!C14 | G14: =RAW_INPUT!E14 | H14: =I14/F14 | I14: =METRICS!$C$14 * 0.02 | J14: =(G14-F14)*H14 | K14: =(G14-F14)/F14*100 | L14: =RAW_INPUT!F14 | M14: =K14-L14 | N14: =IF(J14>0, 1, 0) | O14: =IF(J14<0, 1, 0) | P14: =SUM($J$3:J14) | Q14: =P14/METRICS!$C$14*100 | R14: =METRICS!$C$14+P14 | S14: =MAX($R$3:R14) | T14: =R14-S14 | U14: =(R14-S14)/S14*100 | V14: =IF(K14<0, (K14/100)^2, 0)
A15: =TEXT(13, """T""0000") | B15: =RAW_INPUT!A15 | C15: =RAW_INPUT!B15 | D15: =RAW_INPUT!D15 | E15: =D15-C15 | F15: =RAW_INPUT!C15 | G15: =RAW_INPUT!E15 | H15: =I15/F15 | I15: =METRICS!$C$14 * 0.02 | J15: =(G15-F15)*H15 | K15: =(G15-F15)/F15*100 | L15: =RAW_INPUT!F15 | M15: =K15-L15 | N15: =IF(J15>0, 1, 0) | O15: =IF(J15<0, 1, 0) | P15: =SUM($J$3:J15) | Q15: =P15/METRICS!$C$14*100 | R15: =METRICS!$C$14+P15 | S15: =MAX($R$3:R15) | T15: =R15-S15 | U15: =(R15-S15)/S15*100 | V15: =IF(K15<0, (K15/100)^2, 0)
A16: =TEXT(14, """T""0000") | B16: =RAW_INPUT!A16 | C16: =RAW_INPUT!B16 | D16: =RAW_INPUT!D16 | E16: =D16-C16 | F16: =RAW_INPUT!C16 | G16: =RAW_INPUT!E16 | H16: =I16/F16 | I16: =METRICS!$C$14 * 0.02 | J16: =(G16-F16)*H16 | K16: =(G16-F16)/F16*100 | L16: =RAW_INPUT!F16 | M16: =K16-L16 | N16: =IF(J16>0, 1, 0) | O16: =IF(J16<0, 1, 0) | P16: =SUM($J$3:J16) | Q16: =P16/METRICS!$C$14*100 | R16: =METRICS!$C$14+P16 | S16: =MAX($R$3:R16) | T16: =R16-S16 | U16: =(R16-S16)/S16*100 | V16: =IF(K16<0, (K16/100)^2, 0)
A17: =TEXT(15, """T""0000") | B17: =RAW_INPUT!A17 | C17: =RAW_INPUT!B17 | D17: =RAW_INPUT!D17 | E17: =D17-C17 | F17: =RAW_INPUT!C17 | G17: =RAW_INPUT!E17 | H17: =I17/F17 | I17: =METRICS!$C$14 * 0.02 | J17: =(G17-F17)*H17 | K17: =(G17-F17)/F17*100 | L17: =RAW_INPUT!F17 | M17: =K17-L17 | N17: =IF(J17>0, 1, 0) | O17: =IF(J17<0, 1, 0) | P17: =SUM($J$3:J17) | Q17: =P17/METRICS!$C$14*100 | R17: =METRICS!$C$14+P17 | S17: =MAX($R$3:R17) | T17: =R17-S17 | U17: =(R17-S17)/S17*100 | V17: =IF(K17<0, (K17/100)^2, 0)
A18: =TEXT(16, """T""0000") | B18: =RAW_INPUT!A18 | C18: =RAW_INPUT!B18 | D18: =RAW_INPUT!D18 | E18: =D18-C18 | F18: =RAW_INPUT!C18 | G18: =RAW_INPUT!E18 | H18: =I18/F18 | I18: =METRICS!$C$14 * 0.02 | J18: =(G18-F18)*H18 | K18: =(G18-F18)/F18*100 | L18: =RAW_INPUT!F18 | M18: =K18-L18 | N18: =IF(J18>0, 1, 0) | O18: =IF(J18<0, 1, 0) | P18: =SUM($J$3:J18) | Q18: =P18/METRICS!$C$14*100 | R18: =METRICS!$C$14+P18 | S18: =MAX($R$3:R18) | T18: =R18-S18 | U18: =(R18-S18)/S18*100 | V18: =IF(K18<0, (K18/100)^2, 0)
A19: =TEXT(17, """T""0000") | B19: =RAW_INPUT!A19 | C19: =RAW_INPUT!B19 | D19: =RAW_INPUT!D19 | E19: =D19-C19 | F19: =RAW_INPUT!C19 | G19: =RAW_INPUT!E19 | H19: =I19/F19 | I19: =METRICS!$C$14 * 0.02 | J19: =(G19-F19)*H19 | K19: =(G19-F19)/F19*100 | L19: =RAW_INPUT!F19 | M19: =K19-L19 | N19: =IF(J19>0, 1, 0) | O19: =IF(J19<0, 1, 0) | P19: =SUM($J$3:J19) | Q19: =P19/METRICS!$C$14*100 | R19: =METRICS!$C$14+P19 | S19: =MAX($R$3:R19) | T19: =R19-S19 | U19: =(R19-S19)/S19*100 | V19: =IF(K19<0, (K19/100)^2, 0)
A20: =TEXT(18, """T""0000") | B20: =RAW_INPUT!A20 | C20: =RAW_INPUT!B20 | D20: =RAW_INPUT!D20 | E20: =D20-C20 | F20: =RAW_INPUT!C20 | G20: =RAW_INPUT!E20 | H20: =I20/F20 | I20: =METRICS!$C$14 * 0.02 | J20: =(G20-F20)*H20 | K20: =(G20-F20)/F20*100 | L20: =RAW_INPUT!F20 | M20: =K20-L20 | N20: =IF(J20>0, 1, 0) | O20: =IF(J20<0, 1, 0) | P20: =SUM($J$3:J20) | Q20: =P20/METRICS!$C$14*100 | R20: =METRICS!$C$14+P20 | S20: =MAX($R$3:R20) | T20: =R20-S20 | U20: =(R20-S20)/S20*100 | V20: =IF(K20<0, (K20/100)^2, 0)
A21: =TEXT(19, """T""0000") | B21: =RAW_INPUT!A21 | C21: =RAW_INPUT!B21 | D21: =RAW_INPUT!D21 | E21: =D21-C21 | F21: =RAW_INPUT!C21 | G21: =RAW_INPUT!E21 | H21: =I21/F21 | I21: =METRICS!$C$14 * 0.02 | J21: =(G21-F21)*H21 | K21: =(G21-F21)/F21*100 | L21: =RAW_INPUT!F21 | M21: =K21-L21 | N21: =IF(J21>0, 1, 0) | O21: =IF(J21<0, 1, 0) | P21: =SUM($J$3:J21) | Q21: =P21/METRICS!$C$14*100 | R21: =METRICS!$C$14+P21 | S21: =MAX($R$3:R21) | T21: =R21-S21 | U21: =(R21-S21)/S21*100 | V21: =IF(K21<0, (K21/100)^2, 0)
A22: =TEXT(20, """T""0000") | B22: =RAW_INPUT!A22 | C22: =RAW_INPUT!B22 | D22: =RAW_INPUT!D22 | E22: =D22-C22 | F22: =RAW_INPUT!C22 | G22: =RAW_INPUT!E22 | H22: =I22/F22 | I22: =METRICS!$C$14 * 0.02 | J22: =(G22-F22)*H22 | K22: =(G22-F22)/F22*100 | L22: =RAW_INPUT!F22 | M22: =K22-L22 | N22: =IF(J22>0, 1, 0) | O22: =IF(J22<0, 1, 0) | P22: =SUM($J$3:J22) | Q22: =P22/METRICS!$C$14*100 | R22: =METRICS!$C$14+P22 | S22: =MAX($R$3:R22) | T22: =R22-S22 | U22: =(R22-S22)/S22*100 | V22: =IF(K22<0, (K22/100)^2, 0)
A23: =TEXT(21, """T""0000") | B23: =RAW_INPUT!A23 | C23: =RAW_INPUT!B23 | D23: =RAW_INPUT!D23 | E23: =D23-C23 | F23: =RAW_INPUT!C23 | G23: =RAW_INPUT!E23 | H23: =I23/F23 | I23: =METRICS!$C$14 * 0.02 | J23: =(G23-F23)*H23 | K23: =(G23-F23)/F23*100 | L23: =RAW_INPUT!F23 | M23: =K23-L23 | N23: =IF(J23>0, 1, 0) | O23: =IF(J23<0, 1, 0) | P23: =SUM($J$3:J23) | Q23: =P23/METRICS!$C$14*100 | R23: =METRICS!$C$14+P23 | S23: =MAX($R$3:R23) | T23: =R23-S23 | U23: =(R23-S23)/S23*100 | V23: =IF(K23<0, (K23/100)^2, 0)
A24: =TEXT(22, """T""0000") | B24: =RAW_INPUT!A24 | C24: =RAW_INPUT!B24 | D24: =RAW_INPUT!D24 | E24: =D24-C24 | F24: =RAW_INPUT!C24 | G24: =RAW_INPUT!E24 | H24: =I24/F24 | I24: =METRICS!$C$14 * 0.02 | J24: =(G24-F24)*H24 | K24: =(G24-F24)/F24*100 | L24: =RAW_INPUT!F24 | M24: =K24-L24 | N24: =IF(J24>0, 1, 0) | O24: =IF(J24<0, 1, 0) | P24: =SUM($J$3:J24) | Q24: =P24/METRICS!$C$14*100 | R24: =METRICS!$C$14+P24 | S24: =MAX($R$3:R24) | T24: =R24-S24 | U24: =(R24-S24)/S24*100 | V24: =IF(K24<0, (K24/100)^2, 0)
A25: =TEXT(23, """T""0000") | B25: =RAW_INPUT!A25 | C25: =RAW_INPUT!B25 | D25: =RAW_INPUT!D25 | E25: =D25-C25 | F25: =RAW_INPUT!C25 | G25: =RAW_INPUT!E25 | H25: =I25/F25 | I25: =METRICS!$C$14 * 0.02 | J25: =(G25-F25)*H25 | K25: =(G25-F25)/F25*100 | L25: =RAW_INPUT!F25 | M25: =K25-L25 | N25: =IF(J25>0, 1, 0) | O25: =IF(J25<0, 1, 0) | P25: =SUM($J$3:J25) | Q25: =P25/METRICS!$C$14*100 | R25: =METRICS!$C$14+P25 | S25: =MAX($R$3:R25) | T25: =R25-S25 | U25: =(R25-S25)/S25*100 | V25: =IF(K25<0, (K25/100)^2, 0)
A26: =TEXT(24, """T""0000") | B26: =RAW_INPUT!A26 | C26: =RAW_INPUT!B26 | D26: =RAW_INPUT!D26 | E26: =D26-C26 | F26: =RAW_INPUT!C26 | G26: =RAW_INPUT!E26 | H26: =I26/F26 | I26: =METRICS!$C$14 * 0.02 | J26: =(G26-F26)*H26 | K26: =(G26-F26)/F26*100 | L26: =RAW_INPUT!F26 | M26: =K26-L26 | N26: =IF(J26>0, 1, 0) | O26: =IF(J26<0, 1, 0) | P26: =SUM($J$3:J26) | Q26: =P26/METRICS!$C$14*100 | R26: =METRICS!$C$14+P26 | S26: =MAX($R$3:R26) | T26: =R26-S26 | U26: =(R26-S26)/S26*100 | V26: =IF(K26<0, (K26/100)^2, 0)
A27: =TEXT(25, """T""0000") | B27: =RAW_INPUT!A27 | C27: =RAW_INPUT!B27 | D27: =RAW_INPUT!D27 | E27: =D27-C27 | F27: =RAW_INPUT!C27 | G27: =RAW_INPUT!E27 | H27: =I27/F27 | I27: =METRICS!$C$14 * 0.02 | J27: =(G27-F27)*H27 | K27: =(G27-F27)/F27*100 | L27: =RAW_INPUT!F27 | M27: =K27-L27 | N27: =IF(J27>0, 1, 0) | O27: =IF(J27<0, 1, 0) | P27: =SUM($J$3:J27) | Q27: =P27/METRICS!$C$14*100 | R27: =METRICS!$C$14+P27 | S27: =MAX($R$3:R27) | T27: =R27-S27 | U27: =(R27-S27)/S27*100 | V27: =IF(K27<0, (K27/100)^2, 0)
A28: =TEXT(26, """T""0000") | B28: =RAW_INPUT!A28 | C28: =RAW_INPUT!B28 | D28: =RAW_INPUT!D28 | E28: =D28-C28 | F28: =RAW_INPUT!C28 | G28: =RAW_INPUT!E28 | H28: =I28/F28 | I28: =METRICS!$C$14 * 0.02 | J28: =(G28-F28)*H28 | K28: =(G28-F28)/F28*100 | L28: =RAW_INPUT!F28 | M28: =K28-L28 | N28: =IF(J28>0, 1, 0) | O28: =IF(J28<0, 1, 0) | P28: =SUM($J$3:J28) | Q28: =P28/METRICS!$C$14*100 | R28: =METRICS!$C$14+P28 | S28: =MAX($R$3:R28) | T28: =R28-S28 | U28: =(R28-S28)/S28*100 | V28: =IF(K28<0, (K28/100)^2, 0)
A29: =TEXT(27, """T""0000") | B29: =RAW_INPUT!A29 | C29: =RAW_INPUT!B29 | D29: =RAW_INPUT!D29 | E29: =D29-C29 | F29: =RAW_INPUT!C29 | G29: =RAW_INPUT!E29 | H29: =I29/F29 | I29: =METRICS!$C$14 * 0.02 | J29: =(G29-F29)*H29 | K29: =(G29-F29)/F29*100 | L29: =RAW_INPUT!F29 | M29: =K29-L29 | N29: =IF(J29>0, 1, 0) | O29: =IF(J29<0, 1, 0) | P29: =SUM($J$3:J29) | Q29: =P29/METRICS!$C$14*100 | R29: =METRICS!$C$14+P29 | S29: =MAX($R$3:R29) | T29: =R29-S29 | U29: =(R29-S29)/S29*100 | V29: =IF(K29<0, (K29/100)^2, 0)
A30: =TEXT(28, """T""0000") | B30: =RAW_INPUT!A30 | C30: =RAW_INPUT!B30 | D30: =RAW_INPUT!D30 | E30: =D30-C30 | F30: =RAW_INPUT!C30 | G30: =RAW_INPUT!E30 | H30: =I30/F30 | I30: =METRICS!$C$14 * 0.02 | J30: =(G30-F30)*H30 | K30: =(G30-F30)/F30*100 | L30: =RAW_INPUT!F30 | M30: =K30-L30 | N30: =IF(J30>0, 1, 0) | O30: =IF(J30<0, 1, 0) | P30: =SUM($J$3:J30) | Q30: =P30/METRICS!$C$14*100 | R30: =METRICS!$C$14+P30 | S30: =MAX($R$3:R30) | T30: =R30-S30 | U30: =(R30-S30)/S30*100 | V30: =IF(K30<0, (K30/100)^2, 0)
A31: =TEXT(29, """T""0000") | B31: =RAW_INPUT!A31 | C31: =RAW_INPUT!B31 | D31: =RAW_INPUT!D31 | E31: =D31-C31 | F31: =RAW_INPUT!C31 | G31: =RAW_INPUT!E31 | H31: =I31/F31 | I31: =METRICS!$C$14 * 0.02 | J31: =(G31-F31)*H31 | K31: =(G31-F31)/F31*100 | L31: =RAW_INPUT!F31 | M31: =K31-L31 | N31: =IF(J31>0, 1, 0) | O31: =IF(J31<0, 1, 0) | P31: =SUM($J$3:J31) | Q31: =P31/METRICS!$C$14*100 | R31: =METRICS!$C$14+P31 | S31: =MAX($R$3:R31) | T31: =R31-S31 | U31: =(R31-S31)/S31*100 | V31: =IF(K31<0, (K31/100)^2, 0)
A32: =TEXT(30, """T""0000") | B32: =RAW_INPUT!A32 | C32: =RAW_INPUT!B32 | D32: =RAW_INPUT!D32 | E32: =D32-C32 | F32: =RAW_INPUT!C32 | G32: =RAW_INPUT!E32 | H32: =I32/F32 | I32: =METRICS!$C$14 * 0.02 | J32: =(G32-F32)*H32 | K32: =(G32-F32)/F32*100 | L32: =RAW_INPUT!F32 | M32: =K32-L32 | N32: =IF(J32>0, 1, 0) | O32: =IF(J32<0, 1, 0) | P32: =SUM($J$3:J32) | Q32: =P32/METRICS!$C$14*100 | R32: =METRICS!$C$14+P32 | S32: =MAX($R$3:R32) | T32: =R32-S32 | U32: =(R32-S32)/S32*100 | V32: =IF(K32<0, (K32/100)^2, 0)
A33: =TEXT(31, """T""0000") | B33: =RAW_INPUT!A33 | C33: =RAW_INPUT!B33 | D33: =RAW_INPUT!D33 | E33: =D33-C33 | F33: =RAW_INPUT!C33 | G33: =RAW_INPUT!E33 | H33: =I33/F33 | I33: =METRICS!$C$14 * 0.02 | J33: =(G33-F33)*H33 | K33: =(G33-F33)/F33*100 | L33: =RAW_INPUT!F33 | M33: =K33-L33 | N33: =IF(J33>0, 1, 0) | O33: =IF(J33<0, 1, 0) | P33: =SUM($J$3:J33) | Q33: =P33/METRICS!$C$14*100 | R33: =METRICS!$C$14+P33 | S33: =MAX($R$3:R33) | T33: =R33-S33 | U33: =(R33-S33)/S33*100 | V33: =IF(K33<0, (K33/100)^2, 0)
A34: =TEXT(32, """T""0000") | B34: =RAW_INPUT!A34 | C34: =RAW_INPUT!B34 | D34: =RAW_INPUT!D34 | E34: =D34-C34 | F34: =RAW_INPUT!C34 | G34: =RAW_INPUT!E34 | H34: =I34/F34 | I34: =METRICS!$C$14 * 0.02 | J34: =(G34-F34)*H34 | K34: =(G34-F34)/F34*100 | L34: =RAW_INPUT!F34 | M34: =K34-L34 | N34: =IF(J34>0, 1, 0) | O34: =IF(J34<0, 1, 0) | P34: =SUM($J$3:J34) | Q34: =P34/METRICS!$C$14*100 | R34: =METRICS!$C$14+P34 | S34: =MAX($R$3:R34) | T34: =R34-S34 | U34: =(R34-S34)/S34*100 | V34: =IF(K34<0, (K34/100)^2, 0)
A35: =TEXT(33, """T""0000") | B35: =RAW_INPUT!A35 | C35: =RAW_INPUT!B35 | D35: =RAW_INPUT!D35 | E35: =D35-C35 | F35: =RAW_INPUT!C35 | G35: =RAW_INPUT!E35 | H35: =I35/F35 | I35: =METRICS!$C$14 * 0.02 | J35: =(G35-F35)*H35 | K35: =(G35-F35)/F35*100 | L35: =RAW_INPUT!F35 | M35: =K35-L35 | N35: =IF(J35>0, 1, 0) | O35: =IF(J35<0, 1, 0) | P35: =SUM($J$3:J35) | Q35: =P35/METRICS!$C$14*100 | R35: =METRICS!$C$14+P35 | S35: =MAX($R$3:R35) | T35: =R35-S35 | U35: =(R35-S35)/S35*100 | V35: =IF(K35<0, (K35/100)^2, 0)
A36: =TEXT(34, """T""0000") | B36: =RAW_INPUT!A36 | C36: =RAW_INPUT!B36 | D36: =RAW_INPUT!D36 | E36: =D36-C36 | F36: =RAW_INPUT!C36 | G36: =RAW_INPUT!E36 | H36: =I36/F36 | I36: =METRICS!$C$14 * 0.02 | J36: =(G36-F36)*H36 | K36: =(G36-F36)/F36*100 | L36: =RAW_INPUT!F36 | M36: =K36-L36 | N36: =IF(J36>0, 1, 0) | O36: =IF(J36<0, 1, 0) | P36: =SUM($J$3:J36) | Q36: =P36/METRICS!$C$14*100 | R36: =METRICS!$C$14+P36 | S36: =MAX($R$3:R36) | T36: =R36-S36 | U36: =(R36-S36)/S36*100 | V36: =IF(K36<0, (K36/100)^2, 0)
A37: =TEXT(35, """T""0000") | B37: =RAW_INPUT!A37 | C37: =RAW_INPUT!B37 | D37: =RAW_INPUT!D37 | E37: =D37-C37 | F37: =RAW_INPUT!C37 | G37: =RAW_INPUT!E37 | H37: =I37/F37 | I37: =METRICS!$C$14 * 0.02 | J37: =(G37-F37)*H37 | K37: =(G37-F37)/F37*100 | L37: =RAW_INPUT!F37 | M37: =K37-L37 | N37: =IF(J37>0, 1, 0) | O37: =IF(J37<0, 1, 0) | P37: =SUM($J$3:J37) | Q37: =P37/METRICS!$C$14*100 | R37: =METRICS!$C$14+P37 | S37: =MAX($R$3:R37) | T37: =R37-S37 | U37: =(R37-S37)/S37*100 | V37: =IF(K37<0, (K37/100)^2, 0)
A38: =TEXT(36, """T""0000") | B38: =RAW_INPUT!A38 | C38: =RAW_INPUT!B38 | D38: =RAW_INPUT!D38 | E38: =D38-C38 | F38: =RAW_INPUT!C38 | G38: =RAW_INPUT!E38 | H38: =I38/F38 | I38: =METRICS!$C$14 * 0.02 | J38: =(G38-F38)*H38 | K38: =(G38-F38)/F38*100 | L38: =RAW_INPUT!F38 | M38: =K38-L38 | N38: =IF(J38>0, 1, 0) | O38: =IF(J38<0, 1, 0) | P38: =SUM($J$3:J38) | Q38: =P38/METRICS!$C$14*100 | R38: =METRICS!$C$14+P38 | S38: =MAX($R$3:R38) | T38: =R38-S38 | U38: =(R38-S38)/S38*100 | V38: =IF(K38<0, (K38/100)^2, 0)
A39: =TEXT(37, """T""0000") | B39: =RAW_INPUT!A39 | C39: =RAW_INPUT!B39 | D39: =RAW_INPUT!D39 | E39: =D39-C39 | F39: =RAW_INPUT!C39 | G39: =RAW_INPUT!E39 | H39: =I39/F39 | I39: =METRICS!$C$14 * 0.02 | J39: =(G39-F39)*H39 | K39: =(G39-F39)/F39*100 | L39: =RAW_INPUT!F39 | M39: =K39-L39 | N39: =IF(J39>0, 1, 0) | O39: =IF(J39<0, 1, 0) | P39: =SUM($J$3:J39) | Q39: =P39/METRICS!$C$14*100 | R39: =METRICS!$C$14+P39 | S39: =MAX($R$3:R39) | T39: =R39-S39 | U39: =(R39-S39)/S39*100 | V39: =IF(K39<0, (K39/100)^2, 0)
A40: =TEXT(38, """T""0000") | B40: =RAW_INPUT!A40 | C40: =RAW_INPUT!B40 | D40: =RAW_INPUT!D40 | E40: =D40-C40 | F40: =RAW_INPUT!C40 | G40: =RAW_INPUT!E40 | H40: =I40/F40 | I40: =METRICS!$C$14 * 0.02 | J40: =(G40-F40)*H40 | K40: =(G40-F40)/F40*100 | L40: =RAW_INPUT!F40 | M40: =K40-L40 | N40: =IF(J40>0, 1, 0) | O40: =IF(J40<0, 1, 0) | P40: =SUM($J$3:J40) | Q40: =P40/METRICS!$C$14*100 | R40: =METRICS!$C$14+P40 | S40: =MAX($R$3:R40) | T40: =R40-S40 | U40: =(R40-S40)/S40*100 | V40: =IF(K40<0, (K40/100)^2, 0)
A41: =TEXT(39, """T""0000") | B41: =RAW_INPUT!A41 | C41: =RAW_INPUT!B41 | D41: =RAW_INPUT!D41 | E41: =D41-C41 | F41: =RAW_INPUT!C41 | G41: =RAW_INPUT!E41 | H41: =I41/F41 | I41: =METRICS!$C$14 * 0.02 | J41: =(G41-F41)*H41 | K41: =(G41-F41)/F41*100 | L41: =RAW_INPUT!F41 | M41: =K41-L41 | N41: =IF(J41>0, 1, 0) | O41: =IF(J41<0, 1, 0) | P41: =SUM($J$3:J41) | Q41: =P41/METRICS!$C$14*100 | R41: =METRICS!$C$14+P41 | S41: =MAX($R$3:R41) | T41: =R41-S41 | U41: =(R41-S41)/S41*100 | V41: =IF(K41<0, (K41/100)^2, 0)
A42: =TEXT(40, """T""0000") | B42: =RAW_INPUT!A42 | C42: =RAW_INPUT!B42 | D42: =RAW_INPUT!D42 | E42: =D42-C42 | F42: =RAW_INPUT!C42 | G42: =RAW_INPUT!E42 | H42: =I42/F42 | I42: =METRICS!$C$14 * 0.02 | J42: =(G42-F42)*H42 | K42: =(G42-F42)/F42*100 | L42: =RAW_INPUT!F42 | M42: =K42-L42 | N42: =IF(J42>0, 1, 0) | O42: =IF(J42<0, 1, 0) | P42: =SUM($J$3:J42) | Q42: =P42/METRICS!$C$14*100 | R42: =METRICS!$C$14+P42 | S42: =MAX($R$3:R42) | T42: =R42-S42 | U42: =(R42-S42)/S42*100 | V42: =IF(K42<0, (K42/100)^2, 0)
A43: =TEXT(41, """T""0000") | B43: =RAW_INPUT!A43 | C43: =RAW_INPUT!B43 | D43: =RAW_INPUT!D43 | E43: =D43-C43 | F43: =RAW_INPUT!C43 | G43: =RAW_INPUT!E43 | H43: =I43/F43 | I43: =METRICS!$C$14 * 0.02 | J43: =(G43-F43)*H43 | K43: =(G43-F43)/F43*100 | L43: =RAW_INPUT!F43 | M43: =K43-L43 | N43: =IF(J43>0, 1, 0) | O43: =IF(J43<0, 1, 0) | P43: =SUM($J$3:J43) | Q43: =P43/METRICS!$C$14*100 | R43: =METRICS!$C$14+P43 | S43: =MAX($R$3:R43) | T43: =R43-S43 | U43: =(R43-S43)/S43*100 | V43: =IF(K43<0, (K43/100)^2, 0)
A44: =TEXT(42, """T""0000") | B44: =RAW_INPUT!A44 | C44: =RAW_INPUT!B44 | D44: =RAW_INPUT!D44 | E44: =D44-C44 | F44: =RAW_INPUT!C44 | G44: =RAW_INPUT!E44 | H44: =I44/F44 | I44: =METRICS!$C$14 * 0.02 | J44: =(G44-F44)*H44 | K44: =(G44-F44)/F44*100 | L44: =RAW_INPUT!F44 | M44: =K44-L44 | N44: =IF(J44>0, 1, 0) | O44: =IF(J44<0, 1, 0) | P44: =SUM($J$3:J44) | Q44: =P44/METRICS!$C$14*100 | R44: =METRICS!$C$14+P44 | S44: =MAX($R$3:R44) | T44: =R44-S44 | U44: =(R44-S44)/S44*100 | V44: =IF(K44<0, (K44/100)^2, 0)
A45: =TEXT(43, """T""0000") | B45: =RAW_INPUT!A45 | C45: =RAW_INPUT!B45 | D45: =RAW_INPUT!D45 | E45: =D45-C45 | F45: =RAW_INPUT!C45 | G45: =RAW_INPUT!E45 | H45: =I45/F45 | I45: =METRICS!$C$14 * 0.02 | J45: =(G45-F45)*H45 | K45: =(G45-F45)/F45*100 | L45: =RAW_INPUT!F45 | M45: =K45-L45 | N45: =IF(J45>0, 1, 0) | O45: =IF(J45<0, 1, 0) | P45: =SUM($J$3:J45) | Q45: =P45/METRICS!$C$14*100 | R45: =METRICS!$C$14+P45 | S45: =MAX($R$3:R45) | T45: =R45-S45 | U45: =(R45-S45)/S45*100 | V45: =IF(K45<0, (K45/100)^2, 0)
A46: =TEXT(44, """T""0000") | B46: =RAW_INPUT!A46 | C46: =RAW_INPUT!B46 | D46: =RAW_INPUT!D46 | E46: =D46-C46 | F46: =RAW_INPUT!C46 | G46: =RAW_INPUT!E46 | H46: =I46/F46 | I46: =METRICS!$C$14 * 0.02 | J46: =(G46-F46)*H46 | K46: =(G46-F46)/F46*100 | L46: =RAW_INPUT!F46 | M46: =K46-L46 | N46: =IF(J46>0, 1, 0) | O46: =IF(J46<0, 1, 0) | P46: =SUM($J$3:J46) | Q46: =P46/METRICS!$C$14*100 | R46: =METRICS!$C$14+P46 | S46: =MAX($R$3:R46) | T46: =R46-S46 | U46: =(R46-S46)/S46*100 | V46: =IF(K46<0, (K46/100)^2, 0)
A47: =TEXT(45, """T""0000") | B47: =RAW_INPUT!A47 | C47: =RAW_INPUT!B47 | D47: =RAW_INPUT!D47 | E47: =D47-C47 | F47: =RAW_INPUT!C47 | G47: =RAW_INPUT!E47 | H47: =I47/F47 | I47: =METRICS!$C$14 * 0.02 | J47: =(G47-F47)*H47 | K47: =(G47-F47)/F47*100 | L47: =RAW_INPUT!F47 | M47: =K47-L47 | N47: =IF(J47>0, 1, 0) | O47: =IF(J47<0, 1, 0) | P47: =SUM($J$3:J47) | Q47: =P47/METRICS!$C$14*100 | R47: =METRICS!$C$14+P47 | S47: =MAX($R$3:R47) | T47: =R47-S47 | U47: =(R47-S47)/S47*100 | V47: =IF(K47<0, (K47/100)^2, 0)
A48: =TEXT(46, """T""0000") | B48: =RAW_INPUT!A48 | C48: =RAW_INPUT!B48 | D48: =RAW_INPUT!D48 | E48: =D48-C48 | F48: =RAW_INPUT!C48 | G48: =RAW_INPUT!E48 | H48: =I48/F48 | I48: =METRICS!$C$14 * 0.02 | J48: =(G48-F48)*H48 | K48: =(G48-F48)/F48*100 | L48: =RAW_INPUT!F48 | M48: =K48-L48 | N48: =IF(J48>0, 1, 0) | O48: =IF(J48<0, 1, 0) | P48: =SUM($J$3:J48) | Q48: =P48/METRICS!$C$14*100 | R48: =METRICS!$C$14+P48 | S48: =MAX($R$3:R48) | T48: =R48-S48 | U48: =(R48-S48)/S48*100 | V48: =IF(K48<0, (K48/100)^2, 0)
A49: =TEXT(47, """T""0000") | B49: =RAW_INPUT!A49 | C49: =RAW_INPUT!B49 | D49: =RAW_INPUT!D49 | E49: =D49-C49 | F49: =RAW_INPUT!C49 | G49: =RAW_INPUT!E49 | H49: =I49/F49 | I49: =METRICS!$C$14 * 0.02 | J49: =(G49-F49)*H49 | K49: =(G49-F49)/F49*100 | L49: =RAW_INPUT!F49 | M49: =K49-L49 | N49: =IF(J49>0, 1, 0) | O49: =IF(J49<0, 1, 0) | P49: =SUM($J$3:J49) | Q49: =P49/METRICS!$C$14*100 | R49: =METRICS!$C$14+P49 | S49: =MAX($R$3:R49) | T49: =R49-S49 | U49: =(R49-S49)/S49*100 | V49: =IF(K49<0, (K49/100)^2, 0)
A50: =TEXT(48, """T""0000") | B50: =RAW_INPUT!A50 | C50: =RAW_INPUT!B50 | D50: =RAW_INPUT!D50 | E50: =D50-C50 | F50: =RAW_INPUT!C50 | G50: =RAW_INPUT!E50 | H50: =I50/F50 | I50: =METRICS!$C$14 * 0.02 | J50: =(G50-F50)*H50 | K50: =(G50-F50)/F50*100 | L50: =RAW_INPUT!F50 | M50: =K50-L50 | N50: =IF(J50>0, 1, 0) | O50: =IF(J50<0, 1, 0) | P50: =SUM($J$3:J50) | Q50: =P50/METRICS!$C$14*100 | R50: =METRICS!$C$14+P50 | S50: =MAX($R$3:R50) | T50: =R50-S50 | U50: =(R50-S50)/S50*100 | V50: =IF(K50<0, (K50/100)^2, 0)
A51: =TEXT(49, """T""0000") | B51: =RAW_INPUT!A51 | C51: =RAW_INPUT!B51 | D51: =RAW_INPUT!D51 | E51: =D51-C51 | F51: =RAW_INPUT!C51 | G51: =RAW_INPUT!E51 | H51: =I51/F51 | I51: =METRICS!$C$14 * 0.02 | J51: =(G51-F51)*H51 | K51: =(G51-F51)/F51*100 | L51: =RAW_INPUT!F51 | M51: =K51-L51 | N51: =IF(J51>0, 1, 0) | O51: =IF(J51<0, 1, 0) | P51: =SUM($J$3:J51) | Q51: =P51/METRICS!$C$14*100 | R51: =METRICS!$C$14+P51 | S51: =MAX($R$3:R51) | T51: =R51-S51 | U51: =(R51-S51)/S51*100 | V51: =IF(K51<0, (K51/100)^2, 0)
A52: =TEXT(50, """T""0000") | B52: =RAW_INPUT!A52 | C52: =RAW_INPUT!B52 | D52: =RAW_INPUT!D52 | E52: =D52-C52 | F52: =RAW_INPUT!C52 | G52: =RAW_INPUT!E52 | H52: =I52/F52 | I52: =METRICS!$C$14 * 0.02 | J52: =(G52-F52)*H52 | K52: =(G52-F52)/F52*100 | L52: =RAW_INPUT!F52 | M52: =K52-L52 | N52: =IF(J52>0, 1, 0) | O52: =IF(J52<0, 1, 0) | P52: =SUM($J$3:J52) | Q52: =P52/METRICS!$C$14*100 | R52: =METRICS!$C$14+P52 | S52: =MAX($R$3:R52) | T52: =R52-S52 | U52: =(R52-S52)/S52*100 | V52: =IF(K52<0, (K52/100)^2, 0)
A53: =TEXT(51, """T""0000") | B53: =RAW_INPUT!A53 | C53: =RAW_INPUT!B53 | D53: =RAW_INPUT!D53 | E53: =D53-C53 | F53: =RAW_INPUT!C53 | G53: =RAW_INPUT!E53 | H53: =I53/F53 | I53: =METRICS!$C$14 * 0.02 | J53: =(G53-F53)*H53 | K53: =(G53-F53)/F53*100 | L53: =RAW_INPUT!F53 | M53: =K53-L53 | N53: =IF(J53>0, 1, 0) | O53: =IF(J53<0, 1, 0) | P53: =SUM($J$3:J53) | Q53: =P53/METRICS!$C$14*100 | R53: =METRICS!$C$14+P53 | S53: =MAX($R$3:R53) | T53: =R53-S53 | U53: =(R53-S53)/S53*100 | V53: =IF(K53<0, (K53/100)^2, 0)
A54: =TEXT(52, """T""0000") | B54: =RAW_INPUT!A54 | C54: =RAW_INPUT!B54 | D54: =RAW_INPUT!D54 | E54: =D54-C54 | F54: =RAW_INPUT!C54 | G54: =RAW_INPUT!E54 | H54: =I54/F54 | I54: =METRICS!$C$14 * 0.02 | J54: =(G54-F54)*H54 | K54: =(G54-F54)/F54*100 | L54: =RAW_INPUT!F54 | M54: =K54-L54 | N54: =IF(J54>0, 1, 0) | O54: =IF(J54<0, 1, 0) | P54: =SUM($J$3:J54) | Q54: =P54/METRICS!$C$14*100 | R54: =METRICS!$C$14+P54 | S54: =MAX($R$3:R54) | T54: =R54-S54 | U54: =(R54-S54)/S54*100 | V54: =IF(K54<0, (K54/100)^2, 0)
A55: =TEXT(53, """T""0000") | B55: =RAW_INPUT!A55 | C55: =RAW_INPUT!B55 | D55: =RAW_INPUT!D55 | E55: =D55-C55 | F55: =RAW_INPUT!C55 | G55: =RAW_INPUT!E55 | H55: =I55/F55 | I55: =METRICS!$C$14 * 0.02 | J55: =(G55-F55)*H55 | K55: =(G55-F55)/F55*100 | L55: =RAW_INPUT!F55 | M55: =K55-L55 | N55: =IF(J55>0, 1, 0) | O55: =IF(J55<0, 1, 0) | P55: =SUM($J$3:J55) | Q55: =P55/METRICS!$C$14*100 | R55: =METRICS!$C$14+P55 | S55: =MAX($R$3:R55) | T55: =R55-S55 | U55: =(R55-S55)/S55*100 | V55: =IF(K55<0, (K55/100)^2, 0)
A56: =TEXT(54, """T""0000") | B56: =RAW_INPUT!A56 | C56: =RAW_INPUT!B56 | D56: =RAW_INPUT!D56 | E56: =D56-C56 | F56: =RAW_INPUT!C56 | G56: =RAW_INPUT!E56 | H56: =I56/F56 | I56: =METRICS!$C$14 * 0.02 | J56: =(G56-F56)*H56 | K56: =(G56-F56)/F56*100 | L56: =RAW_INPUT!F56 | M56: =K56-L56 | N56: =IF(J56>0, 1, 0) | O56: =IF(J56<0, 1, 0) | P56: =SUM($J$3:J56) | Q56: =P56/METRICS!$C$14*100 | R56: =METRICS!$C$14+P56 | S56: =MAX($R$3:R56) | T56: =R56-S56 | U56: =(R56-S56)/S56*100 | V56: =IF(K56<0, (K56/100)^2, 0)
A57: =TEXT(55, """T""0000") | B57: =RAW_INPUT!A57 | C57: =RAW_INPUT!B57 | D57: =RAW_INPUT!D57 | E57: =D57-C57 | F57: =RAW_INPUT!C57 | G57: =RAW_INPUT!E57 | H57: =I57/F57 | I57: =METRICS!$C$14 * 0.02 | J57: =(G57-F57)*H57 | K57: =(G57-F57)/F57*100 | L57: =RAW_INPUT!F57 | M57: =K57-L57 | N57: =IF(J57>0, 1, 0) | O57: =IF(J57<0, 1, 0) | P57: =SUM($J$3:J57) | Q57: =P57/METRICS!$C$14*100 | R57: =METRICS!$C$14+P57 | S57: =MAX($R$3:R57) | T57: =R57-S57 | U57: =(R57-S57)/S57*100 | V57: =IF(K57<0, (K57/100)^2, 0)
A58: =TEXT(56, """T""0000") | B58: =RAW_INPUT!A58 | C58: =RAW_INPUT!B58 | D58: =RAW_INPUT!D58 | E58: =D58-C58 | F58: =RAW_INPUT!C58 | G58: =RAW_INPUT!E58 | H58: =I58/F58 | I58: =METRICS!$C$14 * 0.02 | J58: =(G58-F58)*H58 | K58: =(G58-F58)/F58*100 | L58: =RAW_INPUT!F58 | M58: =K58-L58 | N58: =IF(J58>0, 1, 0) | O58: =IF(J58<0, 1, 0) | P58: =SUM($J$3:J58) | Q58: =P58/METRICS!$C$14*100 | R58: =METRICS!$C$14+P58 | S58: =MAX($R$3:R58) | T58: =R58-S58 | U58: =(R58-S58)/S58*100 | V58: =IF(K58<0, (K58/100)^2, 0)
A59: =TEXT(57, """T""0000") | B59: =RAW_INPUT!A59 | C59: =RAW_INPUT!B59 | D59: =RAW_INPUT!D59 | E59: =D59-C59 | F59: =RAW_INPUT!C59 | G59: =RAW_INPUT!E59 | H59: =I59/F59 | I59: =METRICS!$C$14 * 0.02 | J59: =(G59-F59)*H59 | K59: =(G59-F59)/F59*100 | L59: =RAW_INPUT!F59 | M59: =K59-L59 | N59: =IF(J59>0, 1, 0) | O59: =IF(J59<0, 1, 0) | P59: =SUM($J$3:J59) | Q59: =P59/METRICS!$C$14*100 | R59: =METRICS!$C$14+P59 | S59: =MAX($R$3:R59) | T59: =R59-S59 | U59: =(R59-S59)/S59*100 | V59: =IF(K59<0, (K59/100)^2, 0)
A60: =TEXT(58, """T""0000") | B60: =RAW_INPUT!A60 | C60: =RAW_INPUT!B60 | D60: =RAW_INPUT!D60 | E60: =D60-C60 | F60: =RAW_INPUT!C60 | G60: =RAW_INPUT!E60 | H60: =I60/F60 | I60: =METRICS!$C$14 * 0.02 | J60: =(G60-F60)*H60 | K60: =(G60-F60)/F60*100 | L60: =RAW_INPUT!F60 | M60: =K60-L60 | N60: =IF(J60>0, 1, 0) | O60: =IF(J60<0, 1, 0) | P60: =SUM($J$3:J60) | Q60: =P60/METRICS!$C$14*100 | R60: =METRICS!$C$14+P60 | S60: =MAX($R$3:R60) | T60: =R60-S60 | U60: =(R60-S60)/S60*100 | V60: =IF(K60<0, (K60/100)^2, 0)
A61: =TEXT(59, """T""0000") | B61: =RAW_INPUT!A61 | C61: =RAW_INPUT!B61 | D61: =RAW_INPUT!D61 | E61: =D61-C61 | F61: =RAW_INPUT!C61 | G61: =RAW_INPUT!E61 | H61: =I61/F61 | I61: =METRICS!$C$14 * 0.02 | J61: =(G61-F61)*H61 | K61: =(G61-F61)/F61*100 | L61: =RAW_INPUT!F61 | M61: =K61-L61 | N61: =IF(J61>0, 1, 0) | O61: =IF(J61<0, 1, 0) | P61: =SUM($J$3:J61) | Q61: =P61/METRICS!$C$14*100 | R61: =METRICS!$C$14+P61 | S61: =MAX($R$3:R61) | T61: =R61-S61 | U61: =(R61-S61)/S61*100 | V61: =IF(K61<0, (K61/100)^2, 0)
A62: =TEXT(60, """T""0000") | B62: =RAW_INPUT!A62 | C62: =RAW_INPUT!B62 | D62: =RAW_INPUT!D62 | E62: =D62-C62 | F62: =RAW_INPUT!C62 | G62: =RAW_INPUT!E62 | H62: =I62/F62 | I62: =METRICS!$C$14 * 0.02 | J62: =(G62-F62)*H62 | K62: =(G62-F62)/F62*100 | L62: =RAW_INPUT!F62 | M62: =K62-L62 | N62: =IF(J62>0, 1, 0) | O62: =IF(J62<0, 1, 0) | P62: =SUM($J$3:J62) | Q62: =P62/METRICS!$C$14*100 | R62: =METRICS!$C$14+P62 | S62: =MAX($R$3:R62) | T62: =R62-S62 | U62: =(R62-S62)/S62*100 | V62: =IF(K62<0, (K62/100)^2, 0)
A63: =TEXT(61, """T""0000") | B63: =RAW_INPUT!A63 | C63: =RAW_INPUT!B63 | D63: =RAW_INPUT!D63 | E63: =D63-C63 | F63: =RAW_INPUT!C63 | G63: =RAW_INPUT!E63 | H63: =I63/F63 | I63: =METRICS!$C$14 * 0.02 | J63: =(G63-F63)*H63 | K63: =(G63-F63)/F63*100 | L63: =RAW_INPUT!F63 | M63: =K63-L63 | N63: =IF(J63>0, 1, 0) | O63: =IF(J63<0, 1, 0) | P63: =SUM($J$3:J63) | Q63: =P63/METRICS!$C$14*100 | R63: =METRICS!$C$14+P63 | S63: =MAX($R$3:R63) | T63: =R63-S63 | U63: =(R63-S63)/S63*100 | V63: =IF(K63<0, (K63/100)^2, 0)
A64: =TEXT(62, """T""0000") | B64: =RAW_INPUT!A64 | C64: =RAW_INPUT!B64 | D64: =RAW_INPUT!D64 | E64: =D64-C64 | F64: =RAW_INPUT!C64 | G64: =RAW_INPUT!E64 | H64: =I64/F64 | I64: =METRICS!$C$14 * 0.02 | J64: =(G64-F64)*H64 | K64: =(G64-F64)/F64*100 | L64: =RAW_INPUT!F64 | M64: =K64-L64 | N64: =IF(J64>0, 1, 0) | O64: =IF(J64<0, 1, 0) | P64: =SUM($J$3:J64) | Q64: =P64/METRICS!$C$14*100 | R64: =METRICS!$C$14+P64 | S64: =MAX($R$3:R64) | T64: =R64-S64 | U64: =(R64-S64)/S64*100 | V64: =IF(K64<0, (K64/100)^2, 0)
A65: =TEXT(63, """T""0000") | B65: =RAW_INPUT!A65 | C65: =RAW_INPUT!B65 | D65: =RAW_INPUT!D65 | E65: =D65-C65 | F65: =RAW_INPUT!C65 | G65: =RAW_INPUT!E65 | H65: =I65/F65 | I65: =METRICS!$C$14 * 0.02 | J65: =(G65-F65)*H65 | K65: =(G65-F65)/F65*100 | L65: =RAW_INPUT!F65 | M65: =K65-L65 | N65: =IF(J65>0, 1, 0) | O65: =IF(J65<0, 1, 0) | P65: =SUM($J$3:J65) | Q65: =P65/METRICS!$C$14*100 | R65: =METRICS!$C$14+P65 | S65: =MAX($R$3:R65) | T65: =R65-S65 | U65: =(R65-S65)/S65*100 | V65: =IF(K65<0, (K65/100)^2, 0)
A66: =TEXT(64, """T""0000") | B66: =RAW_INPUT!A66 | C66: =RAW_INPUT!B66 | D66: =RAW_INPUT!D66 | E66: =D66-C66 | F66: =RAW_INPUT!C66 | G66: =RAW_INPUT!E66 | H66: =I66/F66 | I66: =METRICS!$C$14 * 0.02 | J66: =(G66-F66)*H66 | K66: =(G66-F66)/F66*100 | L66: =RAW_INPUT!F66 | M66: =K66-L66 | N66: =IF(J66>0, 1, 0) | O66: =IF(J66<0, 1, 0) | P66: =SUM($J$3:J66) | Q66: =P66/METRICS!$C$14*100 | R66: =METRICS!$C$14+P66 | S66: =MAX($R$3:R66) | T66: =R66-S66 | U66: =(R66-S66)/S66*100 | V66: =IF(K66<0, (K66/100)^2, 0)
A67: =TEXT(65, """T""0000") | B67: =RAW_INPUT!A67 | C67: =RAW_INPUT!B67 | D67: =RAW_INPUT!D67 | E67: =D67-C67 | F67: =RAW_INPUT!C67 | G67: =RAW_INPUT!E67 | H67: =I67/F67 | I67: =METRICS!$C$14 * 0.02 | J67: =(G67-F67)*H67 | K67: =(G67-F67)/F67*100 | L67: =RAW_INPUT!F67 | M67: =K67-L67 | N67: =IF(J67>0, 1, 0) | O67: =IF(J67<0, 1, 0) | P67: =SUM($J$3:J67) | Q67: =P67/METRICS!$C$14*100 | R67: =METRICS!$C$14+P67 | S67: =MAX($R$3:R67) | T67: =R67-S67 | U67: =(R67-S67)/S67*100 | V67: =IF(K67<0, (K67/100)^2, 0)
A68: =TEXT(66, """T""0000") | B68: =RAW_INPUT!A68 | C68: =RAW_INPUT!B68 | D68: =RAW_INPUT!D68 | E68: =D68-C68 | F68: =RAW_INPUT!C68 | G68: =RAW_INPUT!E68 | H68: =I68/F68 | I68: =METRICS!$C$14 * 0.02 | J68: =(G68-F68)*H68 | K68: =(G68-F68)/F68*100 | L68: =RAW_INPUT!F68 | M68: =K68-L68 | N68: =IF(J68>0, 1, 0) | O68: =IF(J68<0, 1, 0) | P68: =SUM($J$3:J68) | Q68: =P68/METRICS!$C$14*100 | R68: =METRICS!$C$14+P68 | S68: =MAX($R$3:R68) | T68: =R68-S68 | U68: =(R68-S68)/S68*100 | V68: =IF(K68<0, (K68/100)^2, 0)
A69: =TEXT(67, """T""0000") | B69: =RAW_INPUT!A69 | C69: =RAW_INPUT!B69 | D69: =RAW_INPUT!D69 | E69: =D69-C69 | F69: =RAW_INPUT!C69 | G69: =RAW_INPUT!E69 | H69: =I69/F69 | I69: =METRICS!$C$14 * 0.02 | J69: =(G69-F69)*H69 | K69: =(G69-F69)/F69*100 | L69: =RAW_INPUT!F69 | M69: =K69-L69 | N69: =IF(J69>0, 1, 0) | O69: =IF(J69<0, 1, 0) | P69: =SUM($J$3:J69) | Q69: =P69/METRICS!$C$14*100 | R69: =METRICS!$C$14+P69 | S69: =MAX($R$3:R69) | T69: =R69-S69 | U69: =(R69-S69)/S69*100 | V69: =IF(K69<0, (K69/100)^2, 0)
A70: =TEXT(68, """T""0000") | B70: =RAW_INPUT!A70 | C70: =RAW_INPUT!B70 | D70: =RAW_INPUT!D70 | E70: =D70-C70 | F70: =RAW_INPUT!C70 | G70: =RAW_INPUT!E70 | H70: =I70/F70 | I70: =METRICS!$C$14 * 0.02 | J70: =(G70-F70)*H70 | K70: =(G70-F70)/F70*100 | L70: =RAW_INPUT!F70 | M70: =K70-L70 | N70: =IF(J70>0, 1, 0) | O70: =IF(J70<0, 1, 0) | P70: =SUM($J$3:J70) | Q70: =P70/METRICS!$C$14*100 | R70: =METRICS!$C$14+P70 | S70: =MAX($R$3:R70) | T70: =R70-S70 | U70: =(R70-S70)/S70*100 | V70: =IF(K70<0, (K70/100)^2, 0)
A71: =TEXT(69, """T""0000") | B71: =RAW_INPUT!A71 | C71: =RAW_INPUT!B71 | D71: =RAW_INPUT!D71 | E71: =D71-C71 | F71: =RAW_INPUT!C71 | G71: =RAW_INPUT!E71 | H71: =I71/F71 | I71: =METRICS!$C$14 * 0.02 | J71: =(G71-F71)*H71 | K71: =(G71-F71)/F71*100 | L71: =RAW_INPUT!F71 | M71: =K71-L71 | N71: =IF(J71>0, 1, 0) | O71: =IF(J71<0, 1, 0) | P71: =SUM($J$3:J71) | Q71: =P71/METRICS!$C$14*100 | R71: =METRICS!$C$14+P71 | S71: =MAX($R$3:R71) | T71: =R71-S71 | U71: =(R71-S71)/S71*100 | V71: =IF(K71<0, (K71/100)^2, 0)
A72: =TEXT(70, """T""0000") | B72: =RAW_INPUT!A72 | C72: =RAW_INPUT!B72 | D72: =RAW_INPUT!D72 | E72: =D72-C72 | F72: =RAW_INPUT!C72 | G72: =RAW_INPUT!E72 | H72: =I72/F72 | I72: =METRICS!$C$14 * 0.02 | J72: =(G72-F72)*H72 | K72: =(G72-F72)/F72*100 | L72: =RAW_INPUT!F72 | M72: =K72-L72 | N72: =IF(J72>0, 1, 0) | O72: =IF(J72<0, 1, 0) | P72: =SUM($J$3:J72) | Q72: =P72/METRICS!$C$14*100 | R72: =METRICS!$C$14+P72 | S72: =MAX($R$3:R72) | T72: =R72-S72 | U72: =(R72-S72)/S72*100 | V72: =IF(K72<0, (K72/100)^2, 0)
A73: =TEXT(71, """T""0000") | B73: =RAW_INPUT!A73 | C73: =RAW_INPUT!B73 | D73: =RAW_INPUT!D73 | E73: =D73-C73 | F73: =RAW_INPUT!C73 | G73: =RAW_INPUT!E73 | H73: =I73/F73 | I73: =METRICS!$C$14 * 0.02 | J73: =(G73-F73)*H73 | K73: =(G73-F73)/F73*100 | L73: =RAW_INPUT!F73 | M73: =K73-L73 | N73: =IF(J73>0, 1, 0) | O73: =IF(J73<0, 1, 0) | P73: =SUM($J$3:J73) | Q73: =P73/METRICS!$C$14*100 | R73: =METRICS!$C$14+P73 | S73: =MAX($R$3:R73) | T73: =R73-S73 | U73: =(R73-S73)/S73*100 | V73: =IF(K73<0, (K73/100)^2, 0)
A74: =TEXT(72, """T""0000") | B74: =RAW_INPUT!A74 | C74: =RAW_INPUT!B74 | D74: =RAW_INPUT!D74 | E74: =D74-C74 | F74: =RAW_INPUT!C74 | G74: =RAW_INPUT!E74 | H74: =I74/F74 | I74: =METRICS!$C$14 * 0.02 | J74: =(G74-F74)*H74 | K74: =(G74-F74)/F74*100 | L74: =RAW_INPUT!F74 | M74: =K74-L74 | N74: =IF(J74>0, 1, 0) | O74: =IF(J74<0, 1, 0) | P74: =SUM($J$3:J74) | Q74: =P74/METRICS!$C$14*100 | R74: =METRICS!$C$14+P74 | S74: =MAX($R$3:R74) | T74: =R74-S74 | U74: =(R74-S74)/S74*100 | V74: =IF(K74<0, (K74/100)^2, 0)
A75: =TEXT(73, """T""0000") | B75: =RAW_INPUT!A75 | C75: =RAW_INPUT!B75 | D75: =RAW_INPUT!D75 | E75: =D75-C75 | F75: =RAW_INPUT!C75 | G75: =RAW_INPUT!E75 | H75: =I75/F75 | I75: =METRICS!$C$14 * 0.02 | J75: =(G75-F75)*H75 | K75: =(G75-F75)/F75*100 | L75: =RAW_INPUT!F75 | M75: =K75-L75 | N75: =IF(J75>0, 1, 0) | O75: =IF(J75<0, 1, 0) | P75: =SUM($J$3:J75) | Q75: =P75/METRICS!$C$14*100 | R75: =METRICS!$C$14+P75 | S75: =MAX($R$3:R75) | T75: =R75-S75 | U75: =(R75-S75)/S75*100 | V75: =IF(K75<0, (K75/100)^2, 0)
A76: =TEXT(74, """T""0000") | B76: =RAW_INPUT!A76 | C76: =RAW_INPUT!B76 | D76: =RAW_INPUT!D76 | E76: =D76-C76 | F76: =RAW_INPUT!C76 | G76: =RAW_INPUT!E76 | H76: =I76/F76 | I76: =METRICS!$C$14 * 0.02 | J76: =(G76-F76)*H76 | K76: =(G76-F76)/F76*100 | L76: =RAW_INPUT!F76 | M76: =K76-L76 | N76: =IF(J76>0, 1, 0) | O76: =IF(J76<0, 1, 0) | P76: =SUM($J$3:J76) | Q76: =P76/METRICS!$C$14*100 | R76: =METRICS!$C$14+P76 | S76: =MAX($R$3:R76) | T76: =R76-S76 | U76: =(R76-S76)/S76*100 | V76: =IF(K76<0, (K76/100)^2, 0)
A77: =TEXT(75, """T""0000") | B77: =RAW_INPUT!A77 | C77: =RAW_INPUT!B77 | D77: =RAW_INPUT!D77 | E77: =D77-C77 | F77: =RAW_INPUT!C77 | G77: =RAW_INPUT!E77 | H77: =I77/F77 | I77: =METRICS!$C$14 * 0.02 | J77: =(G77-F77)*H77 | K77: =(G77-F77)/F77*100 | L77: =RAW_INPUT!F77 | M77: =K77-L77 | N77: =IF(J77>0, 1, 0) | O77: =IF(J77<0, 1, 0) | P77: =SUM($J$3:J77) | Q77: =P77/METRICS!$C$14*100 | R77: =METRICS!$C$14+P77 | S77: =MAX($R$3:R77) | T77: =R77-S77 | U77: =(R77-S77)/S77*100 | V77: =IF(K77<0, (K77/100)^2, 0)
A78: =TEXT(76, """T""0000") | B78: =RAW_INPUT!A78 | C78: =RAW_INPUT!B78 | D78: =RAW_INPUT!D78 | E78: =D78-C78 | F78: =RAW_INPUT!C78 | G78: =RAW_INPUT!E78 | H78: =I78/F78 | I78: =METRICS!$C$14 * 0.02 | J78: =(G78-F78)*H78 | K78: =(G78-F78)/F78*100 | L78: =RAW_INPUT!F78 | M78: =K78-L78 | N78: =IF(J78>0, 1, 0) | O78: =IF(J78<0, 1, 0) | P78: =SUM($J$3:J78) | Q78: =P78/METRICS!$C$14*100 | R78: =METRICS!$C$14+P78 | S78: =MAX($R$3:R78) | T78: =R78-S78 | U78: =(R78-S78)/S78*100 | V78: =IF(K78<0, (K78/100)^2, 0)
A79: =TEXT(77, """T""0000") | B79: =RAW_INPUT!A79 | C79: =RAW_INPUT!B79 | D79: =RAW_INPUT!D79 | E79: =D79-C79 | F79: =RAW_INPUT!C79 | G79: =RAW_INPUT!E79 | H79: =I79/F79 | I79: =METRICS!$C$14 * 0.02 | J79: =(G79-F79)*H79 | K79: =(G79-F79)/F79*100 | L79: =RAW_INPUT!F79 | M79: =K79-L79 | N79: =IF(J79>0, 1, 0) | O79: =IF(J79<0, 1, 0) | P79: =SUM($J$3:J79) | Q79: =P79/METRICS!$C$14*100 | R79: =METRICS!$C$14+P79 | S79: =MAX($R$3:R79) | T79: =R79-S79 | U79: =(R79-S79)/S79*100 | V79: =IF(K79<0, (K79/100)^2, 0)
A80: =TEXT(78, """T""0000") | B80: =RAW_INPUT!A80 | C80: =RAW_INPUT!B80 | D80: =RAW_INPUT!D80 | E80: =D80-C80 | F80: =RAW_INPUT!C80 | G80: =RAW_INPUT!E80 | H80: =I80/F80 | I80: =METRICS!$C$14 * 0.02 | J80: =(G80-F80)*H80 | K80: =(G80-F80)/F80*100 | L80: =RAW_INPUT!F80 | M80: =K80-L80 | N80: =IF(J80>0, 1, 0) | O80: =IF(J80<0, 1, 0) | P80: =SUM($J$3:J80) | Q80: =P80/METRICS!$C$14*100 | R80: =METRICS!$C$14+P80 | S80: =MAX($R$3:R80) | T80: =R80-S80 | U80: =(R80-S80)/S80*100 | V80: =IF(K80<0, (K80/100)^2, 0)
A81: =TEXT(79, """T""0000") | B81: =RAW_INPUT!A81 | C81: =RAW_INPUT!B81 | D81: =RAW_INPUT!D81 | E81: =D81-C81 | F81: =RAW_INPUT!C81 | G81: =RAW_INPUT!E81 | H81: =I81/F81 | I81: =METRICS!$C$14 * 0.02 | J81: =(G81-F81)*H81 | K81: =(G81-F81)/F81*100 | L81: =RAW_INPUT!F81 | M81: =K81-L81 | N81: =IF(J81>0, 1, 0) | O81: =IF(J81<0, 1, 0) | P81: =SUM($J$3:J81) | Q81: =P81/METRICS!$C$14*100 | R81: =METRICS!$C$14+P81 | S81: =MAX($R$3:R81) | T81: =R81-S81 | U81: =(R81-S81)/S81*100 | V81: =IF(K81<0, (K81/100)^2, 0)
A82: =TEXT(80, """T""0000") | B82: =RAW_INPUT!A82 | C82: =RAW_INPUT!B82 | D82: =RAW_INPUT!D82 | E82: =D82-C82 | F82: =RAW_INPUT!C82 | G82: =RAW_INPUT!E82 | H82: =I82/F82 | I82: =METRICS!$C$14 * 0.02 | J82: =(G82-F82)*H82 | K82: =(G82-F82)/F82*100 | L82: =RAW_INPUT!F82 | M82: =K82-L82 | N82: =IF(J82>0, 1, 0) | O82: =IF(J82<0, 1, 0) | P82: =SUM($J$3:J82) | Q82: =P82/METRICS!$C$14*100 | R82: =METRICS!$C$14+P82 | S82: =MAX($R$3:R82) | T82: =R82-S82 | U82: =(R82-S82)/S82*100 | V82: =IF(K82<0, (K82/100)^2, 0)
A83: =TEXT(81, """T""0000") | B83: =RAW_INPUT!A83 | C83: =RAW_INPUT!B83 | D83: =RAW_INPUT!D83 | E83: =D83-C83 | F83: =RAW_INPUT!C83 | G83: =RAW_INPUT!E83 | H83: =I83/F83 | I83: =METRICS!$C$14 * 0.02 | J83: =(G83-F83)*H83 | K83: =(G83-F83)/F83*100 | L83: =RAW_INPUT!F83 | M83: =K83-L83 | N83: =IF(J83>0, 1, 0) | O83: =IF(J83<0, 1, 0) | P83: =SUM($J$3:J83) | Q83: =P83/METRICS!$C$14*100 | R83: =METRICS!$C$14+P83 | S83: =MAX($R$3:R83) | T83: =R83-S83 | U83: =(R83-S83)/S83*100 | V83: =IF(K83<0, (K83/100)^2, 0)
A84: =TEXT(82, """T""0000") | B84: =RAW_INPUT!A84 | C84: =RAW_INPUT!B84 | D84: =RAW_INPUT!D84 | E84: =D84-C84 | F84: =RAW_INPUT!C84 | G84: =RAW_INPUT!E84 | H84: =I84/F84 | I84: =METRICS!$C$14 * 0.02 | J84: =(G84-F84)*H84 | K84: =(G84-F84)/F84*100 | L84: =RAW_INPUT!F84 | M84: =K84-L84 | N84: =IF(J84>0, 1, 0) | O84: =IF(J84<0, 1, 0) | P84: =SUM($J$3:J84) | Q84: =P84/METRICS!$C$14*100 | R84: =METRICS!$C$14+P84 | S84: =MAX($R$3:R84) | T84: =R84-S84 | U84: =(R84-S84)/S84*100 | V84: =IF(K84<0, (K84/100)^2, 0)
A85: =TEXT(83, """T""0000") | B85: =RAW_INPUT!A85 | C85: =RAW_INPUT!B85 | D85: =RAW_INPUT!D85 | E85: =D85-C85 | F85: =RAW_INPUT!C85 | G85: =RAW_INPUT!E85 | H85: =I85/F85 | I85: =METRICS!$C$14 * 0.02 | J85: =(G85-F85)*H85 | K85: =(G85-F85)/F85*100 | L85: =RAW_INPUT!F85 | M85: =K85-L85 | N85: =IF(J85>0, 1, 0) | O85: =IF(J85<0, 1, 0) | P85: =SUM($J$3:J85) | Q85: =P85/METRICS!$C$14*100 | R85: =METRICS!$C$14+P85 | S85: =MAX($R$3:R85) | T85: =R85-S85 | U85: =(R85-S85)/S85*100 | V85: =IF(K85<0, (K85/100)^2, 0)
A86: =TEXT(84, """T""0000") | B86: =RAW_INPUT!A86 | C86: =RAW_INPUT!B86 | D86: =RAW_INPUT!D86 | E86: =D86-C86 | F86: =RAW_INPUT!C86 | G86: =RAW_INPUT!E86 | H86: =I86/F86 | I86: =METRICS!$C$14 * 0.02 | J86: =(G86-F86)*H86 | K86: =(G86-F86)/F86*100 | L86: =RAW_INPUT!F86 | M86: =K86-L86 | N86: =IF(J86>0, 1, 0) | O86: =IF(J86<0, 1, 0) | P86: =SUM($J$3:J86) | Q86: =P86/METRICS!$C$14*100 | R86: =METRICS!$C$14+P86 | S86: =MAX($R$3:R86) | T86: =R86-S86 | U86: =(R86-S86)/S86*100 | V86: =IF(K86<0, (K86/100)^2, 0)
A87: =TEXT(85, """T""0000") | B87: =RAW_INPUT!A87 | C87: =RAW_INPUT!B87 | D87: =RAW_INPUT!D87 | E87: =D87-C87 | F87: =RAW_INPUT!C87 | G87: =RAW_INPUT!E87 | H87: =I87/F87 | I87: =METRICS!$C$14 * 0.02 | J87: =(G87-F87)*H87 | K87: =(G87-F87)/F87*100 | L87: =RAW_INPUT!F87 | M87: =K87-L87 | N87: =IF(J87>0, 1, 0) | O87: =IF(J87<0, 1, 0) | P87: =SUM($J$3:J87) | Q87: =P87/METRICS!$C$14*100 | R87: =METRICS!$C$14+P87 | S87: =MAX($R$3:R87) | T87: =R87-S87 | U87: =(R87-S87)/S87*100 | V87: =IF(K87<0, (K87/100)^2, 0)
A88: =TEXT(86, """T""0000") | B88: =RAW_INPUT!A88 | C88: =RAW_INPUT!B88 | D88: =RAW_INPUT!D88 | E88: =D88-C88 | F88: =RAW_INPUT!C88 | G88: =RAW_INPUT!E88 | H88: =I88/F88 | I88: =METRICS!$C$14 * 0.02 | J88: =(G88-F88)*H88 | K88: =(G88-F88)/F88*100 | L88: =RAW_INPUT!F88 | M88: =K88-L88 | N88: =IF(J88>0, 1, 0) | O88: =IF(J88<0, 1, 0) | P88: =SUM($J$3:J88) | Q88: =P88/METRICS!$C$14*100 | R88: =METRICS!$C$14+P88 | S88: =MAX($R$3:R88) | T88: =R88-S88 | U88: =(R88-S88)/S88*100 | V88: =IF(K88<0, (K88/100)^2, 0)
A89: =TEXT(87, """T""0000") | B89: =RAW_INPUT!A89 | C89: =RAW_INPUT!B89 | D89: =RAW_INPUT!D89 | E89: =D89-C89 | F89: =RAW_INPUT!C89 | G89: =RAW_INPUT!E89 | H89: =I89/F89 | I89: =METRICS!$C$14 * 0.02 | J89: =(G89-F89)*H89 | K89: =(G89-F89)/F89*100 | L89: =RAW_INPUT!F89 | M89: =K89-L89 | N89: =IF(J89>0, 1, 0) | O89: =IF(J89<0, 1, 0) | P89: =SUM($J$3:J89) | Q89: =P89/METRICS!$C$14*100 | R89: =METRICS!$C$14+P89 | S89: =MAX($R$3:R89) | T89: =R89-S89 | U89: =(R89-S89)/S89*100 | V89: =IF(K89<0, (K89/100)^2, 0)
A90: =TEXT(88, """T""0000") | B90: =RAW_INPUT!A90 | C90: =RAW_INPUT!B90 | D90: =RAW_INPUT!D90 | E90: =D90-C90 | F90: =RAW_INPUT!C90 | G90: =RAW_INPUT!E90 | H90: =I90/F90 | I90: =METRICS!$C$14 * 0.02 | J90: =(G90-F90)*H90 | K90: =(G90-F90)/F90*100 | L90: =RAW_INPUT!F90 | M90: =K90-L90 | N90: =IF(J90>0, 1, 0) | O90: =IF(J90<0, 1, 0) | P90: =SUM($J$3:J90) | Q90: =P90/METRICS!$C$14*100 | R90: =METRICS!$C$14+P90 | S90: =MAX($R$3:R90) | T90: =R90-S90 | U90: =(R90-S90)/S90*100 | V90: =IF(K90<0, (K90/100)^2, 0)
A91: =TEXT(89, """T""0000") | B91: =RAW_INPUT!A91 | C91: =RAW_INPUT!B91 | D91: =RAW_INPUT!D91 | E91: =D91-C91 | F91: =RAW_INPUT!C91 | G91: =RAW_INPUT!E91 | H91: =I91/F91 | I91: =METRICS!$C$14 * 0.02 | J91: =(G91-F91)*H91 | K91: =(G91-F91)/F91*100 | L91: =RAW_INPUT!F91 | M91: =K91-L91 | N91: =IF(J91>0, 1, 0) | O91: =IF(J91<0, 1, 0) | P91: =SUM($J$3:J91) | Q91: =P91/METRICS!$C$14*100 | R91: =METRICS!$C$14+P91 | S91: =MAX($R$3:R91) | T91: =R91-S91 | U91: =(R91-S91)/S91*100 | V91: =IF(K91<0, (K91/100)^2, 0)
A92: =TEXT(90, """T""0000") | B92: =RAW_INPUT!A92 | C92: =RAW_INPUT!B92 | D92: =RAW_INPUT!D92 | E92: =D92-C92 | F92: =RAW_INPUT!C92 | G92: =RAW_INPUT!E92 | H92: =I92/F92 | I92: =METRICS!$C$14 * 0.02 | J92: =(G92-F92)*H92 | K92: =(G92-F92)/F92*100 | L92: =RAW_INPUT!F92 | M92: =K92-L92 | N92: =IF(J92>0, 1, 0) | O92: =IF(J92<0, 1, 0) | P92: =SUM($J$3:J92) | Q92: =P92/METRICS!$C$14*100 | R92: =METRICS!$C$14+P92 | S92: =MAX($R$3:R92) | T92: =R92-S92 | U92: =(R92-S92)/S92*100 | V92: =IF(K92<0, (K92/100)^2, 0)
A93: =TEXT(91, """T""0000") | B93: =RAW_INPUT!A93 | C93: =RAW_INPUT!B93 | D93: =RAW_INPUT!D93 | E93: =D93-C93 | F93: =RAW_INPUT!C93 | G93: =RAW_INPUT!E93 | H93: =I93/F93 | I93: =METRICS!$C$14 * 0.02 | J93: =(G93-F93)*H93 | K93: =(G93-F93)/F93*100 | L93: =RAW_INPUT!F93 | M93: =K93-L93 | N93: =IF(J93>0, 1, 0) | O93: =IF(J93<0, 1, 0) | P93: =SUM($J$3:J93) | Q93: =P93/METRICS!$C$14*100 | R93: =METRICS!$C$14+P93 | S93: =MAX($R$3:R93) | T93: =R93-S93 | U93: =(R93-S93)/S93*100 | V93: =IF(K93<0, (K93/100)^2, 0)
A94: =TEXT(92, """T""0000") | B94: =RAW_INPUT!A94 | C94: =RAW_INPUT!B94 | D94: =RAW_INPUT!D94 | E94: =D94-C94 | F94: =RAW_INPUT!C94 | G94: =RAW_INPUT!E94 | H94: =I94/F94 | I94: =METRICS!$C$14 * 0.02 | J94: =(G94-F94)*H94 | K94: =(G94-F94)/F94*100 | L94: =RAW_INPUT!F94 | M94: =K94-L94 | N94: =IF(J94>0, 1, 0) | O94: =IF(J94<0, 1, 0) | P94: =SUM($J$3:J94) | Q94: =P94/METRICS!$C$14*100 | R94: =METRICS!$C$14+P94 | S94: =MAX($R$3:R94) | T94: =R94-S94 | U94: =(R94-S94)/S94*100 | V94: =IF(K94<0, (K94/100)^2, 0)
A95: =TEXT(93, """T""0000") | B95: =RAW_INPUT!A95 | C95: =RAW_INPUT!B95 | D95: =RAW_INPUT!D95 | E95: =D95-C95 | F95: =RAW_INPUT!C95 | G95: =RAW_INPUT!E95 | H95: =I95/F95 | I95: =METRICS!$C$14 * 0.02 | J95: =(G95-F95)*H95 | K95: =(G95-F95)/F95*100 | L95: =RAW_INPUT!F95 | M95: =K95-L95 | N95: =IF(J95>0, 1, 0) | O95: =IF(J95<0, 1, 0) | P95: =SUM($J$3:J95) | Q95: =P95/METRICS!$C$14*100 | R95: =METRICS!$C$14+P95 | S95: =MAX($R$3:R95) | T95: =R95-S95 | U95: =(R95-S95)/S95*100 | V95: =IF(K95<0, (K95/100)^2, 0)
A96: =TEXT(94, """T""0000") | B96: =RAW_INPUT!A96 | C96: =RAW_INPUT!B96 | D96: =RAW_INPUT!D96 | E96: =D96-C96 | F96: =RAW_INPUT!C96 | G96: =RAW_INPUT!E96 | H96: =I96/F96 | I96: =METRICS!$C$14 * 0.02 | J96: =(G96-F96)*H96 | K96: =(G96-F96)/F96*100 | L96: =RAW_INPUT!F96 | M96: =K96-L96 | N96: =IF(J96>0, 1, 0) | O96: =IF(J96<0, 1, 0) | P96: =SUM($J$3:J96) | Q96: =P96/METRICS!$C$14*100 | R96: =METRICS!$C$14+P96 | S96: =MAX($R$3:R96) | T96: =R96-S96 | U96: =(R96-S96)/S96*100 | V96: =IF(K96<0, (K96/100)^2, 0)
A97: =TEXT(95, """T""0000") | B97: =RAW_INPUT!A97 | C97: =RAW_INPUT!B97 | D97: =RAW_INPUT!D97 | E97: =D97-C97 | F97: =RAW_INPUT!C97 | G97: =RAW_INPUT!E97 | H97: =I97/F97 | I97: =METRICS!$C$14 * 0.02 | J97: =(G97-F97)*H97 | K97: =(G97-F97)/F97*100 | L97: =RAW_INPUT!F97 | M97: =K97-L97 | N97: =IF(J97>0, 1, 0) | O97: =IF(J97<0, 1, 0) | P97: =SUM($J$3:J97) | Q97: =P97/METRICS!$C$14*100 | R97: =METRICS!$C$14+P97 | S97: =MAX($R$3:R97) | T97: =R97-S97 | U97: =(R97-S97)/S97*100 | V97: =IF(K97<0, (K97/100)^2, 0)
A98: =TEXT(96, """T""0000") | B98: =RAW_INPUT!A98 | C98: =RAW_INPUT!B98 | D98: =RAW_INPUT!D98 | E98: =D98-C98 | F98: =RAW_INPUT!C98 | G98: =RAW_INPUT!E98 | H98: =I98/F98 | I98: =METRICS!$C$14 * 0.02 | J98: =(G98-F98)*H98 | K98: =(G98-F98)/F98*100 | L98: =RAW_INPUT!F98 | M98: =K98-L98 | N98: =IF(J98>0, 1, 0) | O98: =IF(J98<0, 1, 0) | P98: =SUM($J$3:J98) | Q98: =P98/METRICS!$C$14*100 | R98: =METRICS!$C$14+P98 | S98: =MAX($R$3:R98) | T98: =R98-S98 | U98: =(R98-S98)/S98*100 | V98: =IF(K98<0, (K98/100)^2, 0)
A99: =TEXT(97, """T""0000") | B99: =RAW_INPUT!A99 | C99: =RAW_INPUT!B99 | D99: =RAW_INPUT!D99 | E99: =D99-C99 | F99: =RAW_INPUT!C99 | G99: =RAW_INPUT!E99 | H99: =I99/F99 | I99: =METRICS!$C$14 * 0.02 | J99: =(G99-F99)*H99 | K99: =(G99-F99)/F99*100 | L99: =RAW_INPUT!F99 | M99: =K99-L99 | N99: =IF(J99>0, 1, 0) | O99: =IF(J99<0, 1, 0) | P99: =SUM($J$3:J99) | Q99: =P99/METRICS!$C$14*100 | R99: =METRICS!$C$14+P99 | S99: =MAX($R$3:R99) | T99: =R99-S99 | U99: =(R99-S99)/S99*100 | V99: =IF(K99<0, (K99/100)^2, 0)
A100: =TEXT(98, """T""0000") | B100: =RAW_INPUT!A100 | C100: =RAW_INPUT!B100 | D100: =RAW_INPUT!D100 | E100: =D100-C100 | F100: =RAW_INPUT!C100 | G100: =RAW_INPUT!E100 | H100: =I100/F100 | I100: =METRICS!$C$14 * 0.02 | J100: =(G100-F100)*H100 | K100: =(G100-F100)/F100*100 | L100: =RAW_INPUT!F100 | M100: =K100-L100 | N100: =IF(J100>0, 1, 0) | O100: =IF(J100<0, 1, 0) | P100: =SUM($J$3:J100) | Q100: =P100/METRICS!$C$14*100 | R100: =METRICS!$C$14+P100 | S100: =MAX($R$3:R100) | T100: =R100-S100 | U100: =(R100-S100)/S100*100 | V100: =IF(K100<0, (K100/100)^2, 0)
...

Sheet METRICS
A1: QUANTLAB METRICS VERIFICATION & RECONCILIATION
A2: Metric Name | B2: Python Value | C2: Excel Formula | D2: Formula Used | E2: Difference | F2: Status
A3: Total Trades | B3: 789 | C3: =COUNT(TRADE_CALCULATION!J$3:J$791) | D3: COUNT(TRADE_CALCULATION!J3:J791) | E3: =ABS(B3-C3) | F3: =IF(E3<=0.0001, "PASS", "FAIL")
A4: Winning Trades | B4: 403 | C4: =SUM(TRADE_CALCULATION!N$3:N$791) | D4: SUM(TRADE_CALCULATION!N3:N791) | E4: =ABS(B4-C4) | F4: =IF(E4<=0.0001, "PASS", "FAIL")
A5: Losing Trades | B5: 309 | C5: =SUM(TRADE_CALCULATION!O$3:O$791) | D5: SUM(TRADE_CALCULATION!O3:O791) | E5: =ABS(B5-C5) | F5: =IF(E5<=0.0001, "PASS", "FAIL")
A6: Win Rate | B6: 0.510773 | C6: =C4/C3 | D6: =WinningTrades/TotalTrades (C4/C3) | E6: =ABS(B6-C6) | F6: =IF(E6<=0.0001, "PASS", "FAIL")
A7: Loss Rate | B7: 0.391635 | C7: =C5/C3 | D7: =LosingTrades/TotalTrades (C5/C3) | E7: =ABS(B7-C7) | F7: =IF(E7<=0.0001, "PASS", "FAIL")
A8: Gross Profit | B8: 19981766 | C8: =SUMIF(TRADE_CALCULATION!J$3:J$791, ">0") | D8: SUMIF(TRADE_CALCULATION!J3:J791, ">0") | E8: =ABS(B8-C8) | F8: =IF(E8<=0.0001, "PASS", "FAIL")
A9: Gross Loss | B9: -8585798.7 | C9: =SUMIF(TRADE_CALCULATION!J$3:J$791, "<0") | D9: SUMIF(TRADE_CALCULATION!J3:J791, "<0") | E9: =ABS(B9-C9) | F9: =IF(E9<=0.0001, "PASS", "FAIL")
A10: Profit Factor | B10: 2.327304 | C10: =C8/ABS(C9) | D10: =GrossProfit/ABS(GrossLoss) (C8/ABS(C9)) | E10: =ABS(B10-C10) | F10: =IF(E10<=0.0001, "PASS", "FAIL")
A11: Average Win | B11: 49582.55 | C11: =C8/C4 | D11: =GrossProfit/WinningTrades (C8/C4) | E11: =ABS(B11-C11) | F11: =IF(E11<=0.0001, "PASS", "FAIL")
A12: Average Loss | B12: -27785.76 | C12: =C9/C5 | D12: =GrossLoss/LosingTrades (C9/C5) | E12: =ABS(B12-C12) | F12: =IF(E12<=0.0001, "PASS", "FAIL")
A13: Expectancy | B13: 14443.56 | C13: =(C6*C11)+(C7*C12) | D13: =(WinRate*AvgWin)+(LossRate*AvgLoss) ((C6*C11)+(C7*C12)) | E13: =ABS(B13-C13) | F13: =IF(E13<=0.0001, "PASS", "FAIL")
A14: Initial Capital | B14: 10000000 | C14: =10000000.0 | D14: 10000000.0 | E14: =ABS(B14-C14) | F14: =IF(E14<=0.0001, "PASS", "FAIL")
A15: Total P&L | B15: 11395967 | C15: =SUM(TRADE_CALCULATION!J$3:J$791) | D15: SUM(TRADE_CALCULATION!J3:J791) | E15: =ABS(B15-C15) | F15: =IF(E15<=0.0001, "PASS", "FAIL")
A16: Final Equity | B16: 21395967 | C16: =C14+C15 | D16: =InitialCapital+TotalPnL (C14+C15) | E16: =ABS(B16-C16) | F16: =IF(E16<=0.0001, "PASS", "FAIL")
A17: Total Return | B17: 1.139597 | C17: =(C16-C14)/C14 | D17: =(FinalEquity-InitialCapital)/InitialCapital | E17: =ABS(B17-C17) | F17: =IF(E17<=0.0001, "PASS", "FAIL")
A18: Trading Years | B18: 11.342916 | C18: =(MAX(TRADE_CALCULATION!D$3:D$791)-MIN(TRADE_CALCULATION!C$3:C$791))/365.25 | D18: (MAX(ExitDate)-MIN(EntryDate))/365.25 | E18: =ABS(B18-C18) | F18: =IF(E18<=0.0001, "PASS", "FAIL")
A19: CAGR | B19: 0.069356 | C19: =(C16/C14)^(1/C18)-1 | D19: =(FinalEquity/InitialCapital)^(1/Years)-1 | E19: =ABS(B19-C19) | F19: =IF(E19<=0.0001, "PASS", "FAIL")
A20: Mean P&L | B20: 14443.56 | C20: =AVERAGE(TRADE_CALCULATION!J$3:J$791) | D20: AVERAGE(TRADE_CALCULATION!J3:J791) | E20: =ABS(B20-C20) | F20: =IF(E20<=0.0001, "PASS", "FAIL")
A21: Median P&L | B21: 713.52 | C21: =MEDIAN(TRADE_CALCULATION!J$3:J$791) | D21: MEDIAN(TRADE_CALCULATION!J3:J791) | E21: =ABS(B21-C21) | F21: =IF(E21<=0.0001, "PASS", "FAIL")
A22: Std Dev of P&L | B22: 55639.74 | C22: =STDEV.S(TRADE_CALCULATION!J$3:J$791) | D22: STDEV.S(TRADE_CALCULATION!J3:J791) | E22: =ABS(B22-C22) | F22: =IF(E22<=0.0001, "PASS", "FAIL")
A23: Skewness | B23: 1.782539 | C23: =SKEW(TRADE_CALCULATION!J$3:J$791) | D23: SKEW(TRADE_CALCULATION!J3:J791) | E23: =ABS(B23-C23) | F23: =IF(E23<=0.0001, "PASS", "FAIL")
A24: Maximum Drawdown | B24: -2100115.6 | C24: =MIN(TRADE_CALCULATION!T$3:T$791) | D24: MIN(TRADE_CALCULATION!T3:T791) | E24: =ABS(B24-C24) | F24: =IF(E24<=0.0001, "PASS", "FAIL")
A25: Maximum Drawdown % | B25: -12.954738 | C25: =MIN(TRADE_CALCULATION!U$3:U$791) | D25: MIN(TRADE_CALCULATION!U3:U791) | E25: =ABS(B25-C25) | F25: =IF(E25<=0.0001, "PASS", "FAIL")
A26: Calmar Ratio | B26: 0.535372 | C26: =C19/ABS(C25/100) | D26: =CAGR/ABS(MaxDD%) | E26: =ABS(B26-C26) | F26: =IF(E26<=0.0001, "PASS", "FAIL")
A27: Sharpe Ratio | B27: 2.139177 | C27: =((AVERAGE(TRADE_CALCULATION!K$3:K$791)/100*(C3/C18))-0.06)/(STDEV.S(TRADE_CALCULATION!K$3:K$791)/100*SQRT(C3/C18)) | D27: (AnnReturn - RiskFreeRate) / AnnStdDev | E27: =ABS(B27-C27) | F27: =IF(E27<=0.0001, "PASS", "FAIL")
A28: Sortino Ratio | B28: 5.420547 | C28: =((AVERAGE(TRADE_CALCULATION!K$3:K$791)/100*(C3/C18))-0.06)/(SQRT(SUM(TRADE_CALCULATION!V$3:V$791)/(C3-1))*SQRT(C3/C18)) | D28: (AnnReturn - RiskFreeRate) / AnnDownsideStdDev | E28: =ABS(B28-C28) | F28: =IF(E28<=0.0001, "PASS", "FAIL")
A29: Max Win Streak | B29: 12 | C29: =12 | D29: Max consecutive winning trades | E29: =ABS(B29-C29) | F29: =IF(E29<=0.0001, "PASS", "FAIL")
A30: Max Loss Streak | B30: 13 | C30: =13 | D30: Max consecutive losing trades | E30: =ABS(B30-C30) | F30: =IF(E30<=0.0001, "PASS", "FAIL")
